beepboop/__init__.py
beepboop/bot_manager.py
beepboop/resourcer.py
beepboop-0.1.2.dist-info/DESCRIPTION.rst
beepboop-0.1.2.dist-info/METADATA
beepboop-0.1.2.dist-info/metadata.json
beepboop-0.1.2.dist-info/RECORD
beepboop-0.1.2.dist-info/top_level.txt
beepboop-0.1.2.dist-info/WHEEL
