Metadata-Version: 2.0
Name: beepboop
Version: 0.1.2
Summary: Beep Boop client and Bot Manager
Home-page: https://github.com/BeepBoopHQ/beepboop-py
Author: Beep Boop HQ
Author-email: hello@beepboophq.com
License: MIT
Keywords: beepboop slack bot manager api
Platform: UNKNOWN
Classifier: Intended Audience :: Developers
Classifier: License :: OSI Approved :: MIT License
Classifier: Natural Language :: English
Classifier: Programming Language :: Python
Classifier: Programming Language :: Python :: 2.6
Classifier: Programming Language :: Python :: 2.7
Classifier: Programming Language :: Python :: 3
Classifier: Programming Language :: Python :: 3.3
Classifier: Programming Language :: Python :: 3.4
Requires-Dist: six (==1.10.0)
Requires-Dist: websocket-client (==0.35.0)
